LazyIter/__init__.py
LazyIter/count.py
LazyIter/learn.py
LazyIter/utils.py
LazyIter_teshnizi-0.5.1.dist-info/LICENSE
LazyIter_teshnizi-0.5.1.dist-info/METADATA
LazyIter_teshnizi-0.5.1.dist-info/WHEEL
LazyIter_teshnizi-0.5.1.dist-info/top_level.txt
LazyIter_teshnizi-0.5.1.dist-info/RECORD
