Metadata-Version: 2.1
Name: LazyIter-teshnizi
Version: 0.5.1
Summary: LazyIter ICML2020
Home-page: https://github.com/teshnizi/LazyIter
Author: Ali AhmadiTeshnizi
Author-email: aliahmaditeshnizi@gmail.com
License: UNKNOWN
Platform: UNKNOWN
Classifier: Programming Language :: Python :: 3
Classifier: License :: OSI Approved :: MIT License
Classifier: Operating System :: OS Independent
